{
	"url": "https://shop.anekafoto.com/home/1845-hollyland-tx-furry-windshield-lark-m1-lark-c1.html",
	"name": "Hollyland TX Furry Windshield Lark M1 & Lark C1",
	"brand": "N/A",
	"price": "Rp199,000",
	"description": "The Hollyland TX Furry Windshield is designed to fit perfectly with the Hollyland Lark M1 & C1 wireless microphone transmitters. It is made of high-quality, soft fur that effectively reduces wind noise, providing clear and crisp audio even in harsh weather conditions. The windshield is lightweight, easy to attach, and durable, making it an ideal choice for on-the-go filmmakers.",
	"features": {
		"Key Features :": "Weight for each piece: 2g | Color: Black | Applications: For outdoor wind muff and noise reduction | Recommended for outdoor use and harsh environments to effectively shield off wind noise, easy to install, and not easy to fall off.",
		"Compatibility :": "Lark M1 | Lark C1"
	},
	"images": [],
	"scrapedAt": "2026-04-12T15:26:56.915Z"
}