{
	"url": "https://shop.anekafoto.com/home/2259-ailite-dry-cabinet-gp5-15l.html",
	"name": "Ailite Dry Cabinet GP5-15L",
	"brand": "N/A",
	"price": "Rp1,025,000",
	"description": "AILITE Dry Cabinet is a special tool or cabinet box that can be used for storage media for your photography equipment such as camera bodies, lenses, batteries, filters, vertical grips, flashes and many more.",
	"features": {
		"Key Features:": "Weight : 3500 g | Dimensions : 29 × 28 × 29 cm"
	},
	"images": [],
	"scrapedAt": "2026-04-12T15:23:20.736Z"
}