{
	"id": "9QYJMzBP2V3GY0I",
	"json": "{\"id\":\"9QYJMzBP2V3GY0I\",\"url\":\"https://shop.anekafoto.com/17-lighting-studio\",\"loadedUrl\":\"https://shop.anekafoto.com/17-lighting-studio\",\"uniqueKey\":\"https://shop.anekafoto.com/17-lighting-studio\",\"method\":\"GET\",\"noRetry\":false,\"retryCount\":0,\"errorMessages\":[],\"headers\":{},\"userData\":{\"label\":\"DETAIL\",\"__crawlee\":{\"crawlDepth\":1,\"enqueueStrategy\":\"same-hostname\",\"state\":4}},\"handledAt\":\"2026-04-12T15:20:09.420Z\"}",
	"method": "GET",
	"orderNo": null,
	"retryCount": 0,
	"uniqueKey": "https://shop.anekafoto.com/17-lighting-studio",
	"url": "https://shop.anekafoto.com/17-lighting-studio"
}