{
	"id": "EeQNvx9gSexf0nM",
	"json": "{\"id\":\"EeQNvx9gSexf0nM\",\"url\":\"https://shop.anekafoto.com/home/2104-fog-machine.html\",\"loadedUrl\":\"https://shop.anekafoto.com/home/2104-fog-machine.html\",\"uniqueKey\":\"https://shop.anekafoto.com/home/2104-fog-machine.html\",\"method\":\"GET\",\"noRetry\":false,\"retryCount\":0,\"errorMessages\":[],\"headers\":{},\"userData\":{\"label\":\"DETAIL\",\"__crawlee\":{\"crawlDepth\":2,\"enqueueStrategy\":\"same-hostname\",\"state\":4}},\"handledAt\":\"2026-04-12T15:31:33.009Z\"}",
	"method": "GET",
	"orderNo": null,
	"retryCount": 0,
	"uniqueKey": "https://shop.anekafoto.com/home/2104-fog-machine.html",
	"url": "https://shop.anekafoto.com/home/2104-fog-machine.html"
}