{
	"id": "PlB47iBtKyxQHCI",
	"json": "{\"id\":\"PlB47iBtKyxQHCI\",\"url\":\"https://shop.anekafoto.com/home/2235-deity-vo-7u-boom-arm-kit.html\",\"loadedUrl\":\"https://shop.anekafoto.com/home/2235-deity-vo-7u-boom-arm-kit.html\",\"uniqueKey\":\"https://shop.anekafoto.com/home/2235-deity-vo-7u-boom-arm-kit.html\",\"method\":\"GET\",\"noRetry\":false,\"retryCount\":0,\"errorMessages\":[],\"headers\":{},\"userData\":{\"label\":\"DETAIL\",\"__crawlee\":{\"crawlDepth\":2,\"enqueueStrategy\":\"same-hostname\",\"state\":4}},\"handledAt\":\"2026-04-12T15:25:13.016Z\"}",
	"method": "GET",
	"orderNo": null,
	"retryCount": 0,
	"uniqueKey": "https://shop.anekafoto.com/home/2235-deity-vo-7u-boom-arm-kit.html",
	"url": "https://shop.anekafoto.com/home/2235-deity-vo-7u-boom-arm-kit.html"
}