{
	"id": "pUVBNqpZ8HxXXyL",
	"json": "{\"id\":\"pUVBNqpZ8HxXXyL\",\"url\":\"https://shop.anekafoto.com/home/3422-ricoh-gr-iiix-hdf-digital-camera.html\",\"loadedUrl\":\"https://shop.anekafoto.com/home/3422-ricoh-gr-iiix-hdf-digital-camera.html\",\"uniqueKey\":\"https://shop.anekafoto.com/home/3422-ricoh-gr-iiix-hdf-digital-camera.html\",\"method\":\"GET\",\"noRetry\":false,\"retryCount\":0,\"errorMessages\":[],\"headers\":{},\"userData\":{\"label\":\"DETAIL\",\"__crawlee\":{\"crawlDepth\":2,\"enqueueStrategy\":\"same-hostname\",\"state\":4}},\"handledAt\":\"2026-04-12T15:30:17.887Z\"}",
	"method": "GET",
	"orderNo": null,
	"retryCount": 0,
	"uniqueKey": "https://shop.anekafoto.com/home/3422-ricoh-gr-iiix-hdf-digital-camera.html",
	"url": "https://shop.anekafoto.com/home/3422-ricoh-gr-iiix-hdf-digital-camera.html"
}